t4_devkit/__init__.py
t4_devkit/common/__init__.py
t4_devkit/common/box.py
t4_devkit/common/color.py
t4_devkit/common/geometry.py
t4_devkit/common/io.py
t4_devkit/common/timestamp.py
t4_devkit/schema/__init__.py
t4_devkit/schema/builder.py
t4_devkit/schema/name.py
t4_devkit/schema/serialize.py
t4_devkit/schema/tables/__init__.py
t4_devkit/schema/tables/attribute.py
t4_devkit/schema/tables/base.py
t4_devkit/schema/tables/calibrated_sensor.py
t4_devkit/schema/tables/category.py
t4_devkit/schema/tables/ego_pose.py
t4_devkit/schema/tables/instance.py
t4_devkit/schema/tables/keypoint.py
t4_devkit/schema/tables/log.py
t4_devkit/schema/tables/map.py
t4_devkit/schema/tables/object_ann.py
t4_devkit/schema/tables/registry.py
t4_devkit/schema/tables/sample.py
t4_devkit/schema/tables/sample_annotation.py
t4_devkit/schema/tables/sample_data.py
t4_devkit/schema/tables/scene.py
t4_devkit/schema/tables/sensor.py
t4_devkit/schema/tables/surface_ann.py
t4_devkit/schema/tables/visibility.py
t4_devkit/tier4.py
t4_devkit/typing.py
t4_devkit-0.1.0.dist-info/METADATA
t4_devkit-0.1.0.dist-info/WHEEL
t4_devkit-0.1.0.dist-info/RECORD
