Metadata-Version: 2.1
Name: t4-devkit
Version: 0.1.0
Summary: A toolkit to load and operate T4 dataset.
Author: Kotaro Uetake
Author-email: kotaro.uetake@tier4.jp
Requires-Python: >=3.10,<3.13
Classifier: Programming Language :: Python :: 3
Classifier: Programming Language :: Python :: 3.10
Classifier: Programming Language :: Python :: 3.11
Classifier: Programming Language :: Python :: 3.12
Requires-Dist: nuscenes-devkit (>=1.1.11,<2.0.0)
Requires-Dist: rerun-sdk (>=0.16.1,<0.17.0)
